{
  "number": 66,
  "title_he": "תהילים",
  "verses": [
    {
      "num": 1,
      "he": "לַ֭מְנַצֵּחַ שִׁ֣יר מִזְמ֑וֹר הָרִ֥יעוּ לֵ֝אלֹהִ֗ים כׇּל־הָאָֽרֶץ׃",
      "he_plain": "למנצח שיר מזמור הריעו לאלהים כל הארץ",
      "translit": "",
      "es": ""
    },
    {
      "num": 2,
      "he": "זַמְּר֥וּ כְבֽוֹד־שְׁמ֑וֹ שִׂ֥ימוּ כָ֝ב֗וֹד תְּהִלָּתֽוֹ׃",
      "he_plain": "זמרו כבוד שמו שימו כבוד תהלתו",
      "translit": "",
      "es": ""
    },
    {
      "num": 3,
      "he": "אִמְר֣וּ לֵ֭אלֹהִים מַה־נּוֹרָ֣א מַעֲשֶׂ֑יךָ בְּרֹ֥ב עֻ֝זְּךָ֗ יְֽכַחֲשׁ֖וּ לְךָ֣ אֹיְבֶֽיךָ׃",
      "he_plain": "אמרו לאלהים מה נורא מעשיך ברב עזך יכחשו לך איביך",
      "translit": "",
      "es": ""
    },
    {
      "num": 4,
      "he": "כׇּל־הָאָ֤רֶץ׀ יִשְׁתַּחֲו֣וּ לְ֭ךָ וִיזַמְּרוּ־לָ֑ךְ יְזַמְּר֖וּ שִׁמְךָ֣ סֶֽלָה׃",
      "he_plain": "כל הארץ ישתחוו לך ויזמרו לך יזמרו שמך סלה",
      "translit": "",
      "es": ""
    },
    {
      "num": 5,
      "he": "לְכ֣וּ וּ֭רְאוּ מִפְעֲל֣וֹת אֱלֹהִ֑ים נוֹרָ֥א עֲ֝לִילָ֗ה עַל־בְּנֵ֥י אָדָֽם׃",
      "he_plain": "לכו וראו מפעלות אלהים נורא עלילה על בני אדם",
      "translit": "",
      "es": ""
    },
    {
      "num": 6,
      "he": "הָ֤פַךְ יָ֨ם׀ לְֽיַבָּשָׁ֗ה בַּ֭נָּהָר יַעַבְר֣וּ בְרָ֑גֶל שָׁ֝֗ם נִשְׂמְחָה־בּֽוֹ׃",
      "he_plain": "הפך ים ליבשה בנהר יעברו ברגל שם נשמחה בו",
      "translit": "",
      "es": ""
    },
    {
      "num": 7,
      "he": "מֹ֘שֵׁ֤ל בִּגְבוּרָת֨וֹ׀ עוֹלָ֗ם עֵ֭ינָיו בַּגּוֹיִ֣ם תִּצְפֶּ֑ינָה הַסּוֹרְרִ֓ים׀ אַל־[יָר֖וּמוּ] (ירימו) לָ֣מוֹ סֶֽלָה׃",
      "he_plain": "משל בגבורתו עולם עיניו בגוים תצפינה הסוררים אל [ירומו] (ירימו) למו סלה",
      "translit": "",
      "es": ""
    },
    {
      "num": 8,
      "he": "בָּרְכ֖וּ עַמִּ֥ים׀אֱלֹהֵ֑ינוּ וְ֝הַשְׁמִ֗יעוּ ק֣וֹל תְּהִלָּתֽוֹ׃",
      "he_plain": "ברכו עמיםאלהינו והשמיעו קול תהלתו",
      "translit": "",
      "es": ""
    },
    {
      "num": 9,
      "he": "הַשָּׂ֣ם נַ֭פְשֵׁנוּ בַּחַיִּ֑ים וְלֹֽא־נָתַ֖ן לַמּ֣וֹט רַגְלֵֽנוּ׃",
      "he_plain": "השם נפשנו בחיים ולא נתן למוט רגלנו",
      "translit": "",
      "es": ""
    },
    {
      "num": 10,
      "he": "כִּֽי־בְחַנְתָּ֥נוּ אֱלֹהִ֑ים צְ֝רַפְתָּ֗נוּ כִּצְרׇף־כָּֽסֶף׃",
      "he_plain": "כי בחנתנו אלהים צרפתנו כצרף כסף",
      "translit": "",
      "es": ""
    },
    {
      "num": 11,
      "he": "הֲבֵאתָ֥נוּ בַמְּצוּדָ֑ה שַׂ֖מְתָּ מוּעָקָ֣ה בְמׇתְנֵֽינוּ׃",
      "he_plain": "הבאתנו במצודה שמת מועקה במתנינו",
      "translit": "",
      "es": ""
    },
    {
      "num": 12,
      "he": "הִרְכַּ֥בְתָּֽ אֱנ֗וֹשׁ לְרֹ֫אשֵׁ֥נוּ בָּֽאנוּ־בָאֵ֥שׁ וּבַמַּ֑יִם וַ֝תּוֹצִיאֵ֗נוּ לָרְוָיָֽה׃",
      "he_plain": "הרכבת אנוש לראשנו באנו באש ובמים ותוציאנו לרויה",
      "translit": "",
      "es": ""
    },
    {
      "num": 13,
      "he": "אָב֣וֹא בֵיתְךָ֣ בְעוֹל֑וֹת אֲשַׁלֵּ֖ם לְךָ֣ נְדָרָֽי׃",
      "he_plain": "אבוא ביתך בעולות אשלם לך נדרי",
      "translit": "",
      "es": ""
    },
    {
      "num": 14,
      "he": "אֲשֶׁר־פָּצ֥וּ שְׂפָתָ֑י וְדִבֶּר־פִּ֝֗י בַּצַּר־לִֽי׃",
      "he_plain": "אשר פצו שפתי ודבר פי בצר לי",
      "translit": "",
      "es": ""
    },
    {
      "num": 15,
      "he": "עֹ֘ל֤וֹת מֵיחִ֣ים אַֽעֲלֶה־לָּ֭ךְ עִם־קְטֹ֣רֶת אֵילִ֑ים אֶ֥עֱשֶֽׂה־בָקָ֖ר עִם־עַתּוּדִ֣ים סֶֽלָה׃",
      "he_plain": "עלות מיחים אעלה לך עם קטרת אילים אעשה בקר עם עתודים סלה",
      "translit": "",
      "es": ""
    },
    {
      "num": 16,
      "he": "לְכוּ־שִׁמְע֣וּ וַ֭אֲסַפְּרָה כׇּל־יִרְאֵ֣י אֱלֹהִ֑ים אֲשֶׁ֖ר עָשָׂ֣ה לְנַפְשִֽׁי׃",
      "he_plain": "לכו שמעו ואספרה כל יראי אלהים אשר עשה לנפשי",
      "translit": "",
      "es": ""
    },
    {
      "num": 17,
      "he": "אֵלָ֥יו פִּֽי־קָרָ֑אתִי וְ֝רוֹמַ֗ם תַּ֣חַת לְשׁוֹנִֽי׃",
      "he_plain": "אליו פי קראתי ורומם תחת לשוני",
      "translit": "",
      "es": ""
    },
    {
      "num": 18,
      "he": "אָ֭וֶן אִם־רָאִ֣יתִי בְלִבִּ֑י לֹ֖א יִשְׁמַ֣ע׀אֲדֹנָֽי׃",
      "he_plain": "און אם ראיתי בלבי לא ישמעאדני",
      "translit": "",
      "es": ""
    },
    {
      "num": 19,
      "he": "אָ֭כֵן שָׁמַ֣ע אֱלֹהִ֑ים הִ֝קְשִׁ֗יב בְּק֣וֹל תְּפִלָּתִֽי׃",
      "he_plain": "אכן שמע אלהים הקשיב בקול תפלתי",
      "translit": "",
      "es": ""
    },
    {
      "num": 20,
      "he": "בָּר֥וּךְ אֱלֹהִ֑ים אֲשֶׁ֥ר לֹֽא־הֵסִ֘יר־תְּפִלָּתִ֥י וְ֝חַסְדּ֗וֹ מֵאִתִּֽי׃ {פ}",
      "he_plain": "ברוך אלהים אשר לא הסיר תפלתי וחסדו מאתי {פ}",
      "translit": "",
      "es": ""
    }
  ],
  "audio": ""
}